blitzjs_query/__init__.py
blitzjs_query/blitz.py
blitzjs_query/blitz_http.py
blitzjs_query/blitz_queue.py
blitzjs_query/blitz_socket.py
blitzjs_query/connection.py
blitzjs_query/helpers.py
blitzjs_query/test.py
blitzjs_query-0.0.5.dist-info/DESCRIPTION.rst
blitzjs_query-0.0.5.dist-info/METADATA
blitzjs_query-0.0.5.dist-info/RECORD
blitzjs_query-0.0.5.dist-info/WHEEL
blitzjs_query-0.0.5.dist-info/metadata.json
blitzjs_query-0.0.5.dist-info/top_level.txt
