Metadata-Version: 2.0
Name: blitzjs-query
Version: 0.0.5
Summary: HTTP/Socket.io adapter for the blitz.js framework
Home-page: https://github.com/nexus-devs/pip-blitz-query
Author: Nexus Devs
Author-email: nexus@nexus-stats.com
License: MIT
Requires-Dist: promise
Requires-Dist: pymitter
Requires-Dist: requests
Requires-Dist: socketIO-client
